devnetgen/.gitignore
devnetgen/__init__.py
devnetgen/config.py
devnetgen/constructors/__init__.py
devnetgen/constructors/base_crud_constructors.py
devnetgen/constructors/base_tests_constructors.py
devnetgen/constructors/constructor.py
devnetgen/constructors/sources/controller_constructor.py
devnetgen/constructors/sources/crud_constructors.py
devnetgen/constructors/tests/tests_constructors.py
devnetgen/entities.py
devnetgen/executors/__init__.py
devnetgen/executors/crud_executor.py
devnetgen/executors/executor.py
devnetgen/executors/solution_meta.py
devnetgen/executors/sourcegen_executor.py
devnetgen/executors/summaries_executor.py
devnetgen/executors/tests_executor.py
devnetgen/main.py
devnetgen/pluralize.py
devnetgen/templates/Controller.cs.j2
devnetgen/templates/CreateCommand.cs.j2
devnetgen/templates/CreateDto.cs.j2
devnetgen/templates/DeleteCommand.cs.j2
devnetgen/templates/GetEntitiesQuery.cs.j2
devnetgen/templates/GetEntityGridQuery.cs.j2
devnetgen/templates/GetEntityQuery.cs.j2
devnetgen/templates/LegacyController.cs.j2
devnetgen/templates/UpdateCommand.cs.j2
devnetgen/templates/UpdateDto.cs.j2
devnetgen/templates/Validator.cs.j2
devnetgen/templates/VmTemplate.cs.j2
devnetgen/templates/tests/TestBase.cs.j2
devnetgen/templates/tests/commands/CreateEntityTests.cs.j2
devnetgen/templates/tests/commands/DeleteEntityTests.cs.j2
devnetgen/templates/tests/commands/UpdateEntityTests.cs.j2
devnetgen/templates/tests/queries/GetEntitiesTests.cs.j2
devnetgen/templates/tests/queries/GetEntityGridTests.cs.j2
devnetgen/templates/tests/queries/GetEntityTests.cs.j2
devnetgen-0.2.9.1.dist-info/METADATA
devnetgen-0.2.9.1.dist-info/WHEEL
devnetgen-0.2.9.1.dist-info/entry_points.txt
devnetgen-0.2.9.1.dist-info/RECORD
