Metadata-Version: 2.1
Name: devnetgen
Version: 0.2.9.1
Summary: 
Author: Александр Окунев
Author-email: a.okunev@mininform74.ru
Requires-Python: >=3.10,<4.0
Classifier: Programming Language :: Python :: 3
Classifier: Programming Language :: Python :: 3.10
Classifier: Programming Language :: Python :: 3.11
Classifier: Programming Language :: Python :: 3.12
Requires-Dist: jinja2 (>=3.1.6,<4.0.0)
Requires-Dist: typer (>=0.15.2,<0.16.0)
